text_analysis_project/__init__.py
text_analysis_project/analysis.py
text_analysis_matrix-0.1.0.dist-info/METADATA
text_analysis_matrix-0.1.0.dist-info/WHEEL
text_analysis_matrix-0.1.0.dist-info/top_level.txt
text_analysis_matrix-0.1.0.dist-info/RECORD
