Metadata-Version: 2.4
Name: text-analysis-matrix
Version: 0.1.0
Summary: A simple text analysis Python library
Home-page: https://github.com/eldar/text-analysis-matrix
Author: Eldar Eliyev
Author-email: your_email@example.com
Classifier: Programming Language :: Python :: 3
Classifier: License :: OSI Approved :: MIT License
Classifier: Operating System :: OS Independent
Requires-Python: >=3.7
Dynamic: author
Dynamic: author-email
Dynamic: classifier
Dynamic: description
Dynamic: description-content-type
Dynamic: home-page
Dynamic: requires-python
Dynamic: summary
